h2o_authn/__init__.py
h2o_authn/_version.py
h2o_authn/discovery.py
h2o_authn/error.py
h2o_authn/provider.py
h2o_authn/py.typed
h2o_authn/token.py
h2o_authn-3.1.0.dist-info/METADATA
h2o_authn-3.1.0.dist-info/WHEEL
h2o_authn-3.1.0.dist-info/licenses/LICENSE
h2o_authn-3.1.0.dist-info/RECORD
